causalicp/__init__.py
causalicp/data.py
causalicp/icp.py
causalicp-0.1.1.dist-info/LICENSE.txt
causalicp-0.1.1.dist-info/METADATA
causalicp-0.1.1.dist-info/WHEEL
causalicp-0.1.1.dist-info/top_level.txt
causalicp-0.1.1.dist-info/RECORD
