Metadata-Version: 2.1
Name: causalicp
Version: 0.1.1
Summary: Python implementation of the Invariant Causal Prediction (ICP) algorithm for causal discovery.
Home-page: https://github.com/juangamella/icp
Author: Juan L Gamella
Author-email: juangamella@gmail.com
License: BSD 3-Clause License
Platform: UNKNOWN
Requires-Dist: numpy (>=1.17.3)
Requires-Dist: scipy (>=1.4.0)
Requires-Dist: termcolor (>=1.1.0)
